{
  "resource": "Acts",
  "http_method": "GET",
  "route": "/api/actions",
  "description": "Getting a list of micro actions",
  "explanation": null,
  "parameters": [
    {
      "name": "levels",
      "description": "Filter actions by level (micro, meso or macro)"
    },
    {
      "name": "domains_ids",
      "description": "Filter actions by socio cultural domain"
    }
  ],
  "response_fields": [

  ],
  "requests": [
    {
      "request_method": "GET",
      "request_path": "/api/actions?levels[]=micro",
      "request_body": null,
      "request_headers": {
        "Accept": "application/json; application/undp-cabo-verde-v1+json",
        "Content-Type": "application/json",
        "Host": "undp-cabo-verde.herokuapp.com",
        "Cookie": ""
      },
      "request_query_parameters": {
        "levels": [
          "micro"
        ]
      },
      "request_content_type": "application/json",
      "response_status": 200,
      "response_status_text": "OK",
      "response_body": "{\n  \"actions\": [\n    {\n      \"id\": 15,\n      \"name\": \"Indicator of Department\",\n      \"level\": \"micro\",\n      \"locations\": [\n        {\n          \"id\": 5,\n          \"lat\": \"-60.67911598392676\",\n          \"long\": \"60.604997075338076\"\n        }\n      ]\n    }\n  ],\n  \"meta\": {\n    \"size\": 1,\n    \"cache_date\": \"2015-09-01T10:00:05.488Z\"\n  }\n}",
      "response_headers": {
        "X-Frame-Options": "SAMEORIGIN",
        "X-XSS-Protection": "1; mode=block",
        "X-Content-Type-Options": "nosniff",
        "Content-Type": "application/json; charset=utf-8",
        "ETag": "W/\"b05bd5082302e8a4767fe2d0f838a4bd\"",
        "Cache-Control": "max-age=0, private, must-revalidate",
        "X-Request-Id": "a896b25b-6f36-4e88-87f3-7b4f0f73f2a9",
        "X-Runtime": "0.145740",
        "Content-Length": "208"
      },
      "response_content_type": "application/json; charset=utf-8",
      "curl": "curl \"http://umdp-cabo-verde.herokuapp.com/api/actions?levels[]=micro\" -X GET \\\n\t-H \"Accept: application/json; application/undp-cabo-verde-v1+json\" \\\n\t-H \"Content-Type: application/json\" \\\n\t-H \"Host: undp-cabo-verde.herokuapp.com\" \\\n\t-H \"Cookie: \""
    }
  ]
}