{
  "resource": "Actors",
  "http_method": "GET",
  "route": "/api/actors",
  "description": "Getting a list of micro actors",
  "explanation": null,
  "parameters": [
    {
      "name": "levels",
      "description": "Filter actors by level (micro, meso or macro)"
    },
    {
      "name": "domains_ids",
      "description": "Filter actors by socio cultural domain"
    }
  ],
  "response_fields": [

  ],
  "requests": [
    {
      "request_method": "GET",
      "request_path": "/api/actors?levels[]=micro",
      "request_body": null,
      "request_headers": {
        "Accept": "application/json; application/undp-cabo-verde-v1+json",
        "Content-Type": "application/json",
        "Host": "undp-cabo-verde.herokuapp.com",
        "Cookie": ""
      },
      "request_query_parameters": {
        "levels": [
          "micro"
        ]
      },
      "request_content_type": "application/json",
      "response_status": 200,
      "response_status_text": "OK",
      "response_body": "{\n  \"actors\": [\n    {\n      \"id\": 41,\n      \"name\": \"Director of Department\",\n      \"level\": \"micro\",\n      \"locations\": [\n        {\n          \"id\": 19,\n          \"lat\": \"-23.608096184946874\",\n          \"long\": \"66.7653266954035\"\n        }\n      ]\n    }\n  ],\n  \"meta\": {\n    \"size\": 1,\n    \"cache_date\": \"2015-09-01T10:00:25.466Z\"\n  }\n}",
      "response_headers": {
        "X-Frame-Options": "SAMEORIGIN",
        "X-XSS-Protection": "1; mode=block",
        "X-Content-Type-Options": "nosniff",
        "Content-Type": "application/json; charset=utf-8",
        "ETag": "W/\"d0dfb1c8ca98daeec0d062acd5336216\"",
        "Cache-Control": "max-age=0, private, must-revalidate",
        "X-Request-Id": "ad0cbbff-17e3-4323-95ff-46a39510421c",
        "X-Runtime": "0.163572",
        "Content-Length": "206"
      },
      "response_content_type": "application/json; charset=utf-8",
      "curl": "curl \"http://umdp-cabo-verde.herokuapp.com/api/actors?levels[]=micro\" -X GET \\\n\t-H \"Accept: application/json; application/undp-cabo-verde-v1+json\" \\\n\t-H \"Content-Type: application/json\" \\\n\t-H \"Host: undp-cabo-verde.herokuapp.com\" \\\n\t-H \"Cookie: \""
    }
  ]
}