{
  "resource": "Actors",
  "http_method": "GET",
  "route": "/api/actors/:id",
  "description": "Getting a specific actor with relations",
  "explanation": null,
  "parameters": [

  ],
  "response_fields": [

  ],
  "requests": [
    {
      "request_method": "GET",
      "request_path": "/api/actors/29",
      "request_body": null,
      "request_headers": {
        "Accept": "application/json; application/undp-cabo-verde-v1+json",
        "Content-Type": "application/json",
        "Host": "undp-cabo-verde.herokuapp.com",
        "Cookie": ""
      },
      "request_query_parameters": {
      },
      "request_content_type": "application/json",
      "response_status": 200,
      "response_status_text": "OK",
      "response_body": "{\n  \"actor\": {\n    \"id\": 29,\n    \"level\": \"macro\",\n    \"name\": \"Education Organization\",\n    \"observation\": \"Crapula triduana despirmatio cunae. Tepidus quia depereo. Accendo ademptio ventosus.\",\n    \"locations\": [\n      {\n        \"id\": 37,\n        \"name\": \"Emie Raynor\",\n        \"iso\": \"CV\",\n        \"country\": \"Cape Verde\",\n        \"city\": \"Port Zoiestad\",\n        \"zip_code\": \"89476-6279\",\n        \"state\": \"Utah\",\n        \"district\": \"Manley Treutel\",\n        \"street\": \"39893 Lorna Ridge\",\n        \"web_url\": \"http://stracke.info/leopoldo_greenfelder\",\n        \"lat\": \"1111111\",\n        \"long\": \"-117.66311050870324\",\n        \"main\": true,\n        \"start_date\": \"2014-09-01\",\n        \"end_date\": \"2015-09-01\"\n      }\n    ],\n    \"scale\": \"Global, Clothing, Music, Jewelery, Grocery & Computers\",\n    \"short_name\": \"Dr. Oda Howe\",\n    \"legal_status\": \"Daphne Orn\",\n    \"other_names\": \"Claudia Olson\",\n    \"actors\": {\n      \"parents\": [\n        {\n          \"id\": 25,\n          \"name\": \"Economy Organization\",\n          \"level\": \"macro\",\n          \"locations\": [\n            {\n              \"id\": 32,\n              \"lat\": \"64.44161673222831\",\n              \"long\": \"-53.664073746381206\",\n              \"main\": false\n            },\n            {\n              \"id\": 31,\n              \"lat\": \"-42.378806820329615\",\n              \"long\": \"-105.08479364156632\",\n              \"main\": true\n            }\n          ],\n          \"info\": {\n            \"start_date\": \"2015-08-12\",\n            \"end_date\": \"2015-09-01\",\n            \"title\": \"contains\",\n            \"title_reverse\": \"belongs to\"\n          }\n        }\n      ],\n      \"children\": [\n        {\n          \"id\": 26,\n          \"name\": \"Education Institution\",\n          \"level\": \"macro\",\n          \"locations\": [\n            {\n              \"id\": 33,\n              \"lat\": \"-74.19558572657712\",\n              \"long\": \"25.33030107744534\",\n              \"main\": true\n            }\n          ],\n          \"info\": {\n            \"start_date\": \"2015-08-12\",\n            \"end_date\": \"2015-09-01\",\n            \"title\": \"contains\",\n            \"title_reverse\": \"belongs to\"\n          }\n        },\n        {\n          \"id\": 27,\n          \"name\": \"Department of Education\",\n          \"level\": \"meso\",\n          \"locations\": [\n            {\n              \"id\": 34,\n              \"lat\": \"71.02517073919569\",\n              \"long\": \"-142.42774046214433\",\n              \"main\": true\n            }\n          ],\n          \"info\": {\n            \"start_date\": \"2015-08-12\",\n            \"end_date\": \"2015-09-01\",\n            \"title\": \"contains\",\n            \"title_reverse\": \"belongs to\"\n          }\n        },\n        {\n          \"id\": 28,\n          \"name\": \"Director of Department\",\n          \"level\": \"micro\",\n          \"locations\": [\n            {\n              \"id\": 37,\n              \"lat\": \"1111111\",\n              \"long\": \"-117.66311050870324\",\n              \"main\": true,\n              \"start_date\": \"2014-09-01\",\n              \"end_date\": \"2015-09-01\"\n            }\n          ],\n          \"info\": {\n            \"start_date\": \"2015-08-12\",\n            \"end_date\": \"2015-09-01\",\n            \"title\": \"contains\",\n            \"title_reverse\": \"belongs to\"\n          }\n        }\n      ]\n    },\n    \"actions\": {\n      \"children\": [\n        {\n          \"id\": 1,\n          \"name\": \"Indicator of Department\",\n          \"level\": \"micro\",\n          \"locations\": [\n            {\n              \"id\": 36,\n              \"lat\": \"50.106545712993835\",\n              \"long\": \"38.0744263286544\",\n              \"main\": true,\n              \"start_date\": \"2013-09-01\",\n              \"end_date\": \"2014-09-01\"\n            }\n          ],\n          \"info\": {\n            \"start_date\": \"2015-08-12\",\n            \"end_date\": \"2015-09-01\",\n            \"title\": \"implements\",\n            \"title_reverse\": \"implemented by\"\n          }\n        }\n      ]\n    },\n    \"organization_types\": [\n\n    ],\n    \"socio_cultural_domains\": [\n      {\n        \"id\": 62,\n        \"name\": \"Category two\",\n        \"type\": \"Socio cultural domain\",\n        \"icon_identifier\": null\n      },\n      {\n        \"id\": 72,\n        \"name\": \"Fishery, Beauty, Clothing, Electronics, Automotive & Garden\",\n        \"type\": \"Socio cultural domain\",\n        \"icon_identifier\": null\n      }\n    ],\n    \"other_domains\": [\n      {\n        \"id\": 61,\n        \"name\": \"Category one\",\n        \"type\": \"Other domains\",\n        \"icon_identifier\": null\n      }\n    ],\n    \"comments\": [\n\n    ]\n  }\n}",
      "response_headers": {
        "X-Frame-Options": "SAMEORIGIN",
        "X-XSS-Protection": "1; mode=block",
        "X-Content-Type-Options": "nosniff",
        "Content-Type": "application/json; charset=utf-8",
        "ETag": "W/\"44f57a9fb2bace4fc4cd23ff82de933e\"",
        "Cache-Control": "max-age=0, private, must-revalidate",
        "X-Request-Id": "602638d8-825d-4730-a3f8-038ee02a542b",
        "X-Runtime": "0.207307",
        "Content-Length": "2578"
      },
      "response_content_type": "application/json; charset=utf-8",
      "curl": "curl \"http://umdp-cabo-verde.herokuapp.com/api/actors/29\" -X GET \\\n\t-H \"Accept: application/json; application/undp-cabo-verde-v1+json\" \\\n\t-H \"Content-Type: application/json\" \\\n\t-H \"Host: undp-cabo-verde.herokuapp.com\" \\\n\t-H \"Cookie: \""
    }
  ]
}